pydelfini/__init__.py
pydelfini/client.py
pydelfini/collections.py
pydelfini/exceptions.py
pydelfini/item_io.py
pydelfini/dcmd/__init__.py
pydelfini/dcmd/__main__.py
pydelfini/dcmd/cli.py
pydelfini/dcmd/commands/__init__.py
pydelfini/dcmd/commands/accounts.py
pydelfini/dcmd/commands/admin.py
pydelfini/dcmd/commands/auth.py
pydelfini/dcmd/commands/base_commands.py
pydelfini/dcmd/commands/cde.py
pydelfini/dcmd/commands/collection.py
pydelfini/dcmd/commands/config.py
pydelfini/dcmd/commands/groups.py
pydelfini/dcmd/commands/pdd.py
pydelfini/dcmd/commands/tasks.py
pydelfini/dcmd/commands/users.py
pydelfini/delfini_core/.ignore
pydelfini/delfini_core/.opcignore
pydelfini/delfini_core/__init__.py
pydelfini/delfini_core/client.py
pydelfini/delfini_core/errors.py
pydelfini/delfini_core/login.py
pydelfini/delfini_core/paginator.py
pydelfini/delfini_core/types.py
pydelfini/delfini_core/api/__init__.py
pydelfini/delfini_core/api/account/__init__.py
pydelfini/delfini_core/api/account/account_create_account.py
pydelfini/delfini_core/api/account/account_delete_account.py
pydelfini/delfini_core/api/account/account_get_account.py
pydelfini/delfini_core/api/account/account_get_account_page.py
pydelfini/delfini_core/api/account/account_list_accounts.py
pydelfini/delfini_core/api/account/account_update_account.py
pydelfini/delfini_core/api/account/account_update_account_pages.py
pydelfini/delfini_core/api/admin/__init__.py
pydelfini/delfini_core/api/admin/admin_get_config.py
pydelfini/delfini_core/api/admin/admin_grant_admin.py
pydelfini/delfini_core/api/admin/admin_list_admins.py
pydelfini/delfini_core/api/admin/admin_put_config.py
pydelfini/delfini_core/api/admin/admin_tasks_results.py
pydelfini/delfini_core/api/admin/admin_tasks_schedules.py
pydelfini/delfini_core/api/admin/admin_tasks_stats.py
pydelfini/delfini_core/api/auth/__init__.py
pydelfini/delfini_core/api/auth/auth_activate_session.py
pydelfini/delfini_core/api/auth/auth_authenticate_user.py
pydelfini-1.16.2.dist-info/METADATA
pydelfini-1.16.2.dist-info/WHEEL
pydelfini-1.16.2.dist-info/entry_points.txt
pydelfini-1.16.2.dist-info/top_level.txt
pydelfini-1.16.2.dist-info/RECORD
